cryptoservice/__init__.py
cryptoservice/py.typed
cryptoservice/client/__init__.py
cryptoservice/client/client.py
cryptoservice/config/__init__.py
cryptoservice/config/logging.py
cryptoservice/config/retry.py
cryptoservice/config/settings.py
cryptoservice/exceptions/__init__.py
cryptoservice/exceptions/market_exceptions.py
cryptoservice/models/__init__.py
cryptoservice/models/enums.py
cryptoservice/models/integrity_report.py
cryptoservice/models/market_data.py
cryptoservice/models/market_ticker.py
cryptoservice/models/universe.py
cryptoservice/services/__init__.py
cryptoservice/services/market_service.py
cryptoservice/services/downloaders/__init__.py
cryptoservice/services/downloaders/base_downloader.py
cryptoservice/services/downloaders/kline_downloader.py
cryptoservice/services/downloaders/metrics_downloader.py
cryptoservice/services/downloaders/vision_downloader.py
cryptoservice/services/processors/__init__.py
cryptoservice/services/processors/category_manager.py
cryptoservice/services/processors/data_validator.py
cryptoservice/services/processors/time_range_processor.py
cryptoservice/services/processors/universe_manager.py
cryptoservice/storage/__init__.py
cryptoservice/storage/connection.py
cryptoservice/storage/database.py
cryptoservice/storage/incremental.py
cryptoservice/storage/resampler.py
cryptoservice/storage/schema.py
cryptoservice/storage/exporters/__init__.py
cryptoservice/storage/exporters/csv_exporter.py
cryptoservice/storage/exporters/numpy_exporter.py
cryptoservice/storage/exporters/parquet_exporter.py
cryptoservice/storage/queries/__init__.py
cryptoservice/storage/queries/builder.py
cryptoservice/storage/queries/kline_query.py
cryptoservice/storage/queries/metrics_query.py
cryptoservice/storage/stores/__init__.py
cryptoservice/storage/stores/funding_store.py
cryptoservice/storage/stores/interest_store.py
cryptoservice/storage/stores/kline_store.py
cryptoservice/storage/stores/ratio_store.py
cryptoservice/utils/__init__.py
cryptoservice-1.19.2.dist-info/METADATA
cryptoservice-1.19.2.dist-info/WHEEL
cryptoservice-1.19.2.dist-info/RECORD
