Metadata-Version: 2.4
Name: cryptoservice
Version: 1.19.2
Summary: A cryptocurrency trading info package
Author-email: Minnn <minzzzai.s@gmail.com>
License: MIT
Classifier: License :: OSI Approved :: MIT License
Classifier: Operating System :: OS Independent
Classifier: Programming Language :: Python :: 3
Requires-Python: <3.14,>=3.11
Requires-Dist: aiosqlite>=0.21.0
Requires-Dist: aiosqlitepool>=1.0.0
Requires-Dist: pandas>=2.2.3
Requires-Dist: pydantic-settings>=2.7.1
Requires-Dist: python-binance>=1.0.27
Requires-Dist: pyyaml>=6.0.2
Requires-Dist: requests>=2.32.3
Requires-Dist: rich>=13.9.4
Requires-Dist: setuptools>=80.9.0
Requires-Dist: sqlalchemy>=2.0.39
Requires-Dist: structlog>=24.4.0
Requires-Dist: tomli-w>=1.0.0
Requires-Dist: tomli>=2.2.1
Provides-Extra: dev
Requires-Dist: pre-commit>=2.0.0; extra == 'dev'
Requires-Dist: python-dotenv>=0.15.0; extra == 'dev'
Requires-Dist: ruff>=0.4.0; extra == 'dev'
Provides-Extra: dev-all
Requires-Dist: pre-commit>=2.0.0; extra == 'dev-all'
Requires-Dist: pytest-asyncio>=0.21.0; extra == 'dev-all'
Requires-Dist: pytest-cov>=2.10.0; extra == 'dev-all'
Requires-Dist: pytest>=6.0.0; extra == 'dev-all'
Requires-Dist: python-dotenv>=0.15.0; extra == 'dev-all'
Requires-Dist: ruff>=0.4.0; extra == 'dev-all'
Provides-Extra: docs
Requires-Dist: mkdocs-awesome-pages-plugin>=2.9.0; extra == 'docs'
Requires-Dist: mkdocs-gen-files>=0.5.0; extra == 'docs'
Requires-Dist: mkdocs-git-revision-date-localized-plugin>=1.0; extra == 'docs'
Requires-Dist: mkdocs-literate-nav>=0.6.0; extra == 'docs'
Requires-Dist: mkdocs-material-extensions>=1.3; extra == 'docs'
Requires-Dist: mkdocs-material>=9.0; extra == 'docs'
Requires-Dist: mkdocs-section-index>=0.3.8; extra == 'docs'
Requires-Dist: mkdocstrings[python]>=0.24; extra == 'docs'
Provides-Extra: test
Requires-Dist: pytest-asyncio>=0.21.0; extra == 'test'
Requires-Dist: pytest-cov>=2.10.0; extra == 'test'
Requires-Dist: pytest>=6.0.0; extra == 'test'
